gcrpipe/GCRsim_v02h.py
gcrpipe/__init__.py
gcrpipe/electron_spread2.py
gcrpipe/roman_pipeline_interface.py
gcrpipe/data/SN_m_tot_V2.0.csv
gcrpipe/data/rgb_color_list.txt
gcrpipe-0.1.1.dist-info/METADATA
gcrpipe-0.1.1.dist-info/WHEEL
gcrpipe-0.1.1.dist-info/entry_points.txt
gcrpipe-0.1.1.dist-info/top_level.txt
gcrpipe-0.1.1.dist-info/RECORD
