Metadata-Version: 2.4
Name: gcrpipe
Version: 0.1.1
Summary: Minimal Roman GCR simulation + pixelization pipeline
Author: Anthony Harbo Torres, Christopher Hirata, Zac Brutko, Emily Koivu
License: MIT
Requires-Python: >=3.9
Requires-Dist: numpy
Requires-Dist: scipy
Requires-Dist: pandas
